odoo8_addon_account_locked_line_search-8.0.1.0.0-py2.7-nspkg.pth
odoo8_addon_account_locked_line_search-8.0.1.0.0.dist-info/DESCRIPTION.rst
odoo8_addon_account_locked_line_search-8.0.1.0.0.dist-info/METADATA
odoo8_addon_account_locked_line_search-8.0.1.0.0.dist-info/RECORD
odoo8_addon_account_locked_line_search-8.0.1.0.0.dist-info/WHEEL
odoo8_addon_account_locked_line_search-8.0.1.0.0.dist-info/metadata.json
odoo8_addon_account_locked_line_search-8.0.1.0.0.dist-info/namespace_packages.txt
odoo8_addon_account_locked_line_search-8.0.1.0.0.dist-info/top_level.txt
odoo_addons/account_locked_line_search/README.rst
odoo_addons/account_locked_line_search/__init__.py
odoo_addons/account_locked_line_search/__openerp__.py
odoo_addons/account_locked_line_search/models/__init__.py
odoo_addons/account_locked_line_search/models/account.py
odoo_addons/account_locked_line_search/static/description/icon.png
odoo_addons/account_locked_line_search/views/account_view.xml
